periomod/.DS_Store
periomod/__init__.py
periomod/base.py
periomod/app/.DS_Store
periomod/app/__init__.py
periomod/app/_app.py
periomod/app/_app_helpers.py
periomod/app/_inputprocessor.py
periomod/app/images/.DS_Store
periomod/app/images/logo_app.png
periomod/benchmarking/__init__.py
periomod/benchmarking/_basebenchmark.py
periomod/benchmarking/_baseline.py
periomod/benchmarking/_benchmark.py
periomod/data/__init__.py
periomod/data/_basedata.py
periomod/data/_dataloader.py
periomod/data/_helpers.py
periomod/data/_preprocessing.py
periomod/descriptives/__init__.py
periomod/descriptives/_descriptives.py
periomod/evaluation/__init__.py
periomod/evaluation/_baseeval.py
periomod/evaluation/_eval.py
periomod/inference/__init__.py
periomod/inference/_baseinference.py
periomod/inference/_inference.py
periomod/learner/__init__.py
periomod/learner/_learners.py
periomod/learner/_parameters.py
periomod/resampling/__init__.py
periomod/resampling/_baseresampler.py
periomod/resampling/_resampler.py
periomod/training/__init__.py
periomod/training/_basetrainer.py
periomod/training/_metrics.py
periomod/training/_trainer.py
periomod/tuning/__init__.py
periomod/tuning/_basetuner.py
periomod/tuning/_hebo.py
periomod/tuning/_randomsearch.py
periomod/wrapper/__init__.py
periomod/wrapper/_basewrapper.py
periomod/wrapper/_wrapper.py
periomod-0.1.5.dist-info/LICENSE
periomod-0.1.5.dist-info/WHEEL
periomod-0.1.5.dist-info/METADATA
periomod-0.1.5.dist-info/RECORD
