Metadata-Version: 2.3
Name: periomod
Version: 0.1.5
Summary: Package for short-term periodontal modeling
Author: Tobias Brock, Elias Walter
Requires-Python: >=3.10,<3.12
Classifier: Programming Language :: Python :: 3
Classifier: License :: Other/Proprietary License
Requires-Dist: gradio==4.44.1
Requires-Dist: HEBO==0.3.5
Requires-Dist: hydra-core==1.3.2
Requires-Dist: imbalanced-learn==0.12.3
Requires-Dist: matplotlib==3.9.2
Requires-Dist: numpy==1.24.4
Requires-Dist: openpyxl==3.1.5
Requires-Dist: pandas==2.2.2
Requires-Dist: scikit-learn==1.5.1
Requires-Dist: seaborn==0.13.2
Requires-Dist: shap==0.46.0
Requires-Dist: xgboost==2.1.1
Requires-Dist: ruff==0.6.3 ; extra == "dev"
Requires-Dist: pre-commit ; extra == "dev"
Requires-Dist: py-cpuinfo==9.0.0 ; extra == "dev"
Requires-Dist: uvicorn==0.23.1 ; extra == "dev"
Requires-Dist: mkdocs==1.6.1 ; extra == "docs"
Requires-Dist: mkdocs-material==9.5.43 ; extra == "docs"
Requires-Dist: mkdocstrings==0.26.2 ; extra == "docs"
Requires-Dist: mkdocstrings-python==1.12.2 ; extra == "docs"
Requires-Dist: pytest==8.3.2 ; extra == "tests"
Requires-Dist: unittest ; extra == "tests"
Requires-Dist: coverage ; extra == "tests"
Provides-Extra: dev
Provides-Extra: docs
Provides-Extra: tests
